mtcnn/__init__.py
mtcnn/layer_factory.py
mtcnn/mtcnn.py
mtcnn/network.py
mtcnn/data/__init__.py
mtcnn/data/mtcnn_weights.npy
mtcnn/network/__init__.py
mtcnn/network/factory.py
mtcnn_python-0.6.0.dist-info/LICENSE
mtcnn_python-0.6.0.dist-info/METADATA
mtcnn_python-0.6.0.dist-info/WHEEL
mtcnn_python-0.6.0.dist-info/top_level.txt
mtcnn_python-0.6.0.dist-info/RECORD
