Metadata-Version: 2.1
Name: mtcnn-python
Version: 0.6.0
Summary: mtcnn-python package.
Home-page: https://github.com/leeyunjai/mtcnn-python
Author: UNKNOWN
Author-email: UNKNOWN
License: UNKNOWN
Keywords: mtcnn
Platform: UNKNOWN
Classifier: Natural Language :: English
Classifier: Programming Language :: Python :: 3.7
Classifier: Programming Language :: Python :: 3.8
Requires-Dist: opencv-contrib-python (>=4.5.4.60)
Requires-Dist: tensorflow (==2.9.1)
